Tarea5/demux/with_delay/src/probador.v
module probador( //testbench: signal generator and data monitor
    input [3:0]	data_out0, data_out1,			// From demux1_2 of demux.v
    output reg clk,
    output reg reset_L,			                // To demux1_2 of demux.v
    output reg [3:0]	data_in);
 
   initial
     begin
      $dumpfile("demux_1x2.vcd");               //Dumpfile to make in current folder 
      $dumpvars;                                //Directive to "dump" variables  
         reset_L <= 'b0;
         @(posedge clk);
         reset_L <= 1;                          //set reset to 1 to start the demux
         
         repeat(20)begin                        //run for first 10 cycles of the clock
             @(posedge clk);
             //data_in <= $random % 16;           //use $urandom or $random 
         end

         repeat(10)begin
             @(posedge clk);
             reset_L <= 0;
             //data_in <= $random % 16;           //use $urandom or $random
         end
         
         @(posedge clk);
         reset_L <='b0;
         $finish;                               //finishes storing variables 
     end
    
    always  #2 clk  <= ~clk;                    //"Toggle" each 2*10ns
    always  #20 data_in <= $random % 16;
    initial clk <= 0;
    initial data_in <= 'b0;    
endmodule

Tarea5/demux/no_delay/src/yosys_demux.v
/* Generated by Yosys 0.7 (git sha1 61f6811, gcc 6.2.0-11ubuntu1 -O2 -fdebug-prefix-map=/build/yosys-OIL3SR/yosys-0.7=. -fstack-protector-strong -fPIC -Os) */

(* top =  1  *)
(* src = "src/demux.v:2" *)
module demux(clk, reset_L, data_out0, data_out1, data_in);
  (* src = "src/demux.v:13" *)
  wire [3:0] _00_;
  (* src = "src/demux.v:13" *)
  wire [3:0] _01_;
  (* src = "src/demux.v:13" *)
  wire _02_;
  wire _03_;
  wire _04_;
  wire _05_;
  wire _06_;
  wire _07_;
  wire _08_;
  wire _09_;
  wire _10_;
  (* src = "src/demux.v:3" *)
  input clk;
  (* src = "src/demux.v:5" *)
  input [3:0] data_in;
  (* src = "src/demux.v:4" *)
  output [3:0] data_out0;
  (* src = "src/demux.v:4" *)
  output [3:0] data_out1;
  (* src = "src/demux.v:3" *)
  input reset_L;
  (* src = "src/demux.v:8" *)
  wire s;
  NAND _11_ (
    .A(reset_L),
    .B(s),
    .Y(_04_)
  );
  NOR _12_ (
    .A(_04_),
    .B(_03_),
    .Y(_01_[0])
  );
  NOT _13_ (
    .A(data_in[1]),
    .Y(_05_)
  );
  NOR _14_ (
    .A(_04_),
    .B(_05_),
    .Y(_01_[1])
  );
  NOT _15_ (
    .A(data_in[2]),
    .Y(_06_)
  );
  NOR _16_ (
    .A(_04_),
    .B(_06_),
    .Y(_01_[2])
  );
  NOT _17_ (
    .A(data_in[3]),
    .Y(_07_)
  );
  NOR _18_ (
    .A(_04_),
    .B(_07_),
    .Y(_01_[3])
  );
  NOT _19_ (
    .A(s),
    .Y(_08_)
  );
  NAND _20_ (
    .A(reset_L),
    .B(_08_),
    .Y(_09_)
  );
  NOR _21_ (
    .A(_09_),
    .B(_03_),
    .Y(_00_[0])
  );
  NOR _22_ (
    .A(_09_),
    .B(_05_),
    .Y(_00_[1])
  );
  NOR _23_ (
    .A(_09_),
    .B(_06_),
    .Y(_00_[2])
  );
  NOR _24_ (
    .A(_09_),
    .B(_07_),
    .Y(_00_[3])
  );
  NOT _25_ (
    .A(reset_L),
    .Y(_10_)
  );
  NOR _26_ (
    .A(_10_),
    .B(s),
    .Y(_02_)
  );
  NOT _27_ (
    .A(data_in[0]),
    .Y(_03_)
  );
  DFF _28_ (
    .C(clk),
    .D(_00_[0]),
    .Q(data_out0[0])
  );
  DFF _29_ (
    .C(clk),
    .D(_00_[1]),
    .Q(data_out0[1])
  );
  DFF _30_ (
    .C(clk),
    .D(_00_[2]),
    .Q(data_out0[2])
  );
  DFF _31_ (
    .C(clk),
    .D(_00_[3]),
    .Q(data_out0[3])
  );
  DFF _32_ (
    .C(clk),
    .D(_01_[0]),
    .Q(data_out1[0])
  );
  DFF _33_ (
    .C(clk),
    .D(_01_[1]),
    .Q(data_out1[1])
  );
  DFF _34_ (
    .C(clk),
    .D(_01_[2]),
    .Q(data_out1[2])
  );
  DFF _35_ (
    .C(clk),
    .D(_01_[3]),
    .Q(data_out1[3])
  );
  DFF _36_ (
    .C(clk),
    .D(_02_),
    .Q(s)
  );
endmodule

Tarea5/demux/BancoPrueba.v
`timescale  1ns / 100ps
`include "yosys_demux.v"
`include "probador.v"
`include "cmos_cells.v"

module TestBench;                               //testbench doesn't have ports

    /*AUTOWIRE*/
    // Beginning of automatic wires (for undeclared instantiated-module outputs)
    wire		clk;			// From probador of probador.v
    wire [3:0]		data_in;		// From probador of probador.v
    wire [3:0]		data_out0;		// From dmux of demux.v
    wire [3:0]		data_out1;		// From dmux of demux.v
    wire		reset_L;		// From probador of probador.v
    // End of automatics
   /*AUTOREGINPUT*/

    demux dmux (/*AUTOINST*/
		// Outputs
		.data_out0		(data_out0[3:0]),
		.data_out1		(data_out1[3:0]),
		// Inputs
		.clk			(clk),
		.reset_L		(reset_L),
		.data_in		(data_in[3:0]));

    probador probador (/*AUTOINST*/
		       // Outputs
		       .clk		(clk),
		       .reset_L		(reset_L),
		       .data_in		(data_in[3:0]),
		       // Inputs
		       .data_out0	(data_out0[3:0]),
		       .data_out1	(data_out1[3:0]));
endmodule

Tarea5/demux/with_delay/lib/cmos_cells.v
//https://www.mouser.com/new/Texas-Instruments/ti-sn74aup1g126-buffer-gates/
//SN74AUP1G126 Low-Power Single Bus Buffer Gates
module BUF(A, Y);
input A;
output Y;
assign #(0.15:0.48:0.48) Y = A;
endmodule

//NOT gate SN74LVC1GU04
//http://www.ti.com/product/SN74LVC1GU04/description
module NOT(A, Y);
input A;
output Y;
assign #(0.1:0.3:0.3) Y = ~A;
endmodule

//NAND Gate SN74LVC1G00
//http://www.ti.com/product/SN74LVC1G00/description?keyMatch=nand&tisearch=Search-EN-Everything
module NAND(A, B, Y);
input A, B;
output Y;
assign #(0.1:0.45:0.45) Y = ~(A & B);
endmodule

//NOR gate SN74LVC1G02
//http://www.ti.com/product/SN74LVC1G02/description
module NOR(A, B, Y);
input A, B;
output Y;
assign #(0.1:0.35:0.35) Y = ~(A | B);
endmodule

// Flip-Flop SN74LVC1G175
// http://www.ti.com/product/SN74LVC1G175/description
module DFF(C, D, Q);
input C, D;
output reg Q;
always @(posedge C)
#(0.5:0.7:0.7) Q <= D;
endmodule

//Flip-Flop + Set and Reset signals, just use same values as DFF
module DFFSR(C, D, Q, S, R);
input C, D, S, R;
output reg Q;
always @(posedge C, posedge S, posedge R)
	if (S)
#(0.5:0.7:0.7) 	Q <= 1'b1;
	else if (R)
#(0.5:0.7:0.7) 	Q <= 1'b0;
	else
#(0.5:0.7:0.7) Q <= D;
endmodule

Tarea5/demux/no_delay/demux_1x2.vcd
$date
	Sat Apr 13 16:41:29 2019
$end
$version
	Icarus Verilog
$end
$timescale
	100ps
$end
$scope module BUF $end
$var wire 1 ! A $end
$var wire 1 " Y $end
$upscope $end
$scope module DFFSR $end
$var wire 1 # C $end
$var wire 1 $ D $end
$var wire 1 % R $end
$var wire 1 & S $end
$var reg 1 ' Q $end
$upscope $end
$scope module TestBench $end
$var wire 1 ( reset_L $end
$var wire 4 ) data_out1 [3:0] $end
$var wire 4 * data_out0 [3:0] $end
$var wire 4 + data_in [3:0] $end
$var wire 1 , clk $end
$scope module dmux $end
$var wire 1 - s $end
$var wire 1 ( reset_L $end
$var wire 4 . data_out1 [3:0] $end
$var wire 4 / data_out0 [3:0] $end
$var wire 4 0 data_in [3:0] $end
$var wire 1 , clk $end
$var wire 1 1 _10_ $end
$var wire 1 2 _09_ $end
$var wire 1 3 _08_ $end
$var wire 1 4 _07_ $end
$var wire 1 5 _06_ $end
$var wire 1 6 _05_ $end
$var wire 1 7 _04_ $end
$var wire 1 8 _03_ $end
$var wire 1 9 _02_ $end
$var wire 4 : _01_ [3:0] $end
$var wire 4 ; _00_ [3:0] $end
$scope module _11_ $end
$var wire 1 7 Y $end
$var wire 1 - B $end
$var wire 1 ( A $end
$upscope $end
$scope module _12_ $end
$var wire 1 7 A $end
$var wire 1 < Y $end
$var wire 1 8 B $end
$upscope $end
$scope module _13_ $end
$var wire 1 = A $end
$var wire 1 6 Y $end
$upscope $end
$scope module _14_ $end
$var wire 1 7 A $end
$var wire 1 6 B $end
$var wire 1 > Y $end
$upscope $end
$scope module _15_ $end
$var wire 1 ? A $end
$var wire 1 5 Y $end
$upscope $end
$scope module _16_ $end
$var wire 1 7 A $end
$var wire 1 5 B $end
$var wire 1 @ Y $end
$upscope $end
$scope module _17_ $end
$var wire 1 A A $end
$var wire 1 4 Y $end
$upscope $end
$scope module _18_ $end
$var wire 1 7 A $end
$var wire 1 4 B $end
$var wire 1 B Y $end
$upscope $end
$scope module _19_ $end
$var wire 1 3 Y $end
$var wire 1 - A $end
$upscope $end
$scope module _20_ $end
$var wire 1 3 B $end
$var wire 1 2 Y $end
$var wire 1 ( A $end
$upscope $end
$scope module _21_ $end
$var wire 1 2 A $end
$var wire 1 C Y $end
$var wire 1 8 B $end
$upscope $end
$scope module _22_ $end
$var wire 1 2 A $end
$var wire 1 6 B $end
$var wire 1 D Y $end
$upscope $end
$scope module _23_ $end
$var wire 1 2 A $end
$var wire 1 5 B $end
$var wire 1 E Y $end
$upscope $end
$scope module _24_ $end
$var wire 1 2 A $end
$var wire 1 4 B $end
$var wire 1 F Y $end
$upscope $end
$scope module _25_ $end
$var wire 1 1 Y $end
$var wire 1 ( A $end
$upscope $end
$scope module _26_ $end
$var wire 1 1 A $end
$var wire 1 9 Y $end
$var wire 1 - B $end
$upscope $end
$scope module _27_ $end
$var wire 1 G A $end
$var wire 1 8 Y $end
$upscope $end
$scope module _28_ $end
$var wire 1 H D $end
$var wire 1 , C $end
$var reg 1 I Q $end
$upscope $end
$scope module _29_ $end
$var wire 1 J D $end
$var wire 1 , C $end
$var reg 1 K Q $end
$upscope $end
$scope module _30_ $end
$var wire 1 L D $end
$var wire 1 , C $end
$var reg 1 M Q $end
$upscope $end
$scope module _31_ $end
$var wire 1 N D $end
$var wire 1 , C $end
$var reg 1 O Q $end
$upscope $end
$scope module _32_ $end
$var wire 1 P D $end
$var wire 1 , C $end
$var reg 1 Q Q $end
$upscope $end
$scope module _33_ $end
$var wire 1 R D $end
$var wire 1 , C $end
$var reg 1 S Q $end
$upscope $end
$scope module _34_ $end
$var wire 1 T D $end
$var wire 1 , C $end
$var reg 1 U Q $end
$upscope $end
$scope module _35_ $end
$var wire 1 V D $end
$var wire 1 , C $end
$var reg 1 W Q $end
$upscope $end
$scope module _36_ $end
$var wire 1 9 D $end
$var wire 1 , C $end
$var reg 1 - Q $end
$upscope $end
$upscope $end
$scope module probador $end
$var wire 4 X data_out0 [3:0] $end
$var wire 4 Y data_out1 [3:0] $end
$var reg 1 , clk $end
$var reg 4 Z data_in [3:0] $end
$var reg 1 ( reset_L $end
$upscope $end
$upscope $end
$enddefinitions $end
#0
$dumpvars
b0 Z
bx Y
bx X
xW
0V
xU
0T
xS
0R
xQ
0P
xO
0N
xM
0L
xK
0J
xI
0H
0G
0F
0E
0D
0C
0B
0A
0@
0?
0>
0=
0<
b0 ;
b0 :
09
18
17
16
15
14
x3
12
11
b0 0
bx /
bx .
x-
0,
b0 +
bx *
bx )
0(
x'
z&
z%
z$
z#
z"
z!
$end
#20
19
02
13
01
0I
0K
0M
b0 *
b0 /
b0 X
0O
0Q
0S
0U
b0 )
b0 .
b0 Y
0W
0-
1(
1,
#40
0,
#60
12
09
07
03
1-
1,
#80
0,
#100
02
19
17
13
0-
1,
#120
0,
#140
12
09
07
03
1-
1,
#160
0,
#180
02
19
17
13
0-
1,
#200
1L
b100 ;
1E
05
1?
0,
b100 +
b100 0
b100 Z
#220
0L
b0 ;
0E
1T
b100 :
1@
12
09
07
03
1-
b100 *
b100 /
b100 X
1M
1,
#240
0,
#260
1L
b100 ;
1E
0T
b0 :
0@
02
19
17
13
b0 *
b0 /
b0 X
0M
b100 )
b100 .
b100 Y
1U
0-
1,
#280
0,
#300
0L
b0 ;
0E
1T
b100 :
1@
12
09
07
03
1-
b0 )
b0 .
b0 Y
0U
b100 *
b100 /
b100 X
1M
1,
#320
0,
#340
1L
b100 ;
1E
0T
b0 :
0@
02
19
17
13
b0 *
b0 /
b0 X
0M
b100 )
b100 .
b100 Y
1U
0-
1,
#360
0,
#380
0L
b0 ;
0E
1T
b100 :
1@
12
09
07
03
1-
b0 )
b0 .
b0 Y
0U
b100 *
b100 /
b100 X
1M
1,
#400
1P
0T
1<
b1 :
0@
08
15
1G
0?
0,
b1 +
b1 0
b1 Z
#420
1H
b1 ;
1C
0P
b0 :
0<
02
19
17
13
b0 *
b0 /
b0 X
0M
b1 )
b1 .
b1 Y
1Q
0-
1,
#440
0,
#460
0H
b0 ;
0C
1P
b1 :
1<
12
09
07
03
1-
b0 )
b0 .
b0 Y
0Q
b1 *
b1 /
b1 X
1I
1,
#480
0,
#500
1H
b1 ;
1C
0P
b0 :
0<
02
19
17
13
b0 *
b0 /
b0 X
0I
b1 )
b1 .
b1 Y
1Q
0-
1,
#520
0,
#540
0H
b0 ;
0C
1P
b1 :
1<
12
09
07
03
1-
b0 )
b0 .
b0 Y
0Q
b1 *
b1 /
b1 X
1I
1,
#560
0,
#580
1H
b1 ;
1C
0P
b0 :
0<
02
19
17
13
b0 *
b0 /
b0 X
0I
b1 )
b1 .
b1 Y
1Q
0-
1,
#600
1N
b1001 ;
1F
04
1A
0,
b1001 +
b1001 0
b1001 Z
#620
0H
0N
0C
b0 ;
0F
1P
1V
1<
b1001 :
1B
12
09
07
03
1-
b0 )
b0 .
b0 Y
0Q
1O
b1001 *
b1001 /
b1001 X
1I
1,
#640
0,
#660
1H
1N
1C
b1001 ;
1F
0P
0V
0<
b0 :
0B
02
19
17
13
0I
b0 *
b0 /
b0 X
0O
1Q
b1001 )
b1001 .
b1001 Y
1W
0-
1,
#680
0,
#700
0H
0N
0C
b0 ;
0F
1P
1V
1<
b1001 :
1B
12
09
07
03
1-
0W
b0 )
b0 .
b0 Y
0Q
1O
b1001 *
b1001 /
b1001 X
1I
1,
#720
0,
#740
1H
1N
1C
b1001 ;
1F
0P
0V
0<
b0 :
0B
02
19
17
13
0I
b0 *
b0 /
b0 X
0O
1Q
b1001 )
b1001 .
b1001 Y
1W
0-
1,
#760
0,
#780
0H
0N
0C
b0 ;
0F
1P
1V
1<
b1001 :
1B
12
09
07
03
1-
0W
b0 )
b0 .
b0 Y
0Q
1O
b1001 *
b1001 /
b1001 X
1I
1,
#800
0V
1R
0B
b11 :
1>
14
06
0A
1=
0,
b11 +
b11 0
b11 Z
#820
1H
1J
1C
b11 ;
1D
0P
0R
0<
b0 :
0>
02
19
17
13
0I
b0 *
b0 /
b0 X
0O
1Q
b11 )
b11 .
b11 Y
1S
0-
1,
#840
0,
#860
0H
0J
0C
b0 ;
0D
12
09
11
03
0(
1-
0S
b0 )
b0 .
b0 Y
0Q
1K
b11 *
b11 /
b11 X
1I
1,
#880
0,
#900
13
0I
b0 *
b0 /
b0 X
0K
0-
1,
#920
0,
#940
1,
#960
0,
#980
1,
#1000
04
05
16
1A
1?
0=
0,
b1101 +
b1101 0
b1101 Z
